ucurv/__init__.py
ucurv/meyerwavelet.py
ucurv/ucurv.py
ucurv/util.py
ucurv/zoneplate.py
ucurv-0.1.1.dist-info/METADATA
ucurv-0.1.1.dist-info/WHEEL
ucurv-0.1.1.dist-info/top_level.txt
ucurv-0.1.1.dist-info/RECORD
