Metadata-Version: 2.1
Name: ucurv
Version: 0.1.1
Summary: uniform discrete curvelet transform
Home-page: https://github.com/yud08/ucurv
Author: Duy Nguyen
Author-email: duyn26364@gmail.com
Classifier: Programming Language :: Python :: 3
Classifier: License :: OSI Approved :: MIT License
Classifier: Operating System :: OS Independent
Requires-Python: >=3.6
Requires-Dist: numpy
Requires-Dist: matplotlib
Requires-Dist: pytest
